cohesion_calculator/__init__.py
cohesion_calculator/cohesion.py
cohesion_calculator/log.py
cohesion_calculator/span.py
cohesion_calculator/trace.py
cohesion_measuring-0.1.dist-info/METADATA
cohesion_measuring-0.1.dist-info/WHEEL
cohesion_measuring-0.1.dist-info/top_level.txt
cohesion_measuring-0.1.dist-info/RECORD
