Metadata-Version: 2.1
Name: cohesion_measuring
Version: 0.1
Summary: A Python library for calculating SCOM cohesion value for a microservice
Author: Bianca Kasper
